odoo/addons/project_parent/README.rst
odoo/addons/project_parent/__init__.py
odoo/addons/project_parent/__manifest__.py
odoo/addons/project_parent/demo/project_project_demo.xml
odoo/addons/project_parent/i18n/es.po
odoo/addons/project_parent/i18n/fr.po
odoo/addons/project_parent/i18n/hr.po
odoo/addons/project_parent/i18n/it.po
odoo/addons/project_parent/i18n/nl.po
odoo/addons/project_parent/i18n/nl_NL.po
odoo/addons/project_parent/i18n/project_parent.pot
odoo/addons/project_parent/i18n/pt.po
odoo/addons/project_parent/i18n/pt_BR.po
odoo/addons/project_parent/i18n/sl.po
odoo/addons/project_parent/models/__init__.py
odoo/addons/project_parent/models/project_project.py
odoo/addons/project_parent/readme/CONTRIBUTORS.md
odoo/addons/project_parent/readme/DESCRIPTION.md
odoo/addons/project_parent/readme/USAGE.md
odoo/addons/project_parent/static/description/icon.png
odoo/addons/project_parent/static/description/index.html
odoo/addons/project_parent/tests/__init__.py
odoo/addons/project_parent/tests/test_project_parent.py
odoo/addons/project_parent/views/project_parent_views.xml
odoo_addon_project_parent-18.0.1.0.0.4.dist-info/METADATA
odoo_addon_project_parent-18.0.1.0.0.4.dist-info/WHEEL
odoo_addon_project_parent-18.0.1.0.0.4.dist-info/top_level.txt
odoo_addon_project_parent-18.0.1.0.0.4.dist-info/RECORD
